kxchat/__init__.py
kxchat/cli.py
kxchat/py.typed
kxchat/scripts/chat.py
kxchat-0.1.1.dist-info/METADATA
kxchat-0.1.1.dist-info/WHEEL
kxchat-0.1.1.dist-info/entry_points.txt
kxchat-0.1.1.dist-info/RECORD
