Metadata-Version: 2.4
Name: kxchat
Version: 0.1.1
Summary: Add your description here
Author-email: ksterx <kostonerx@gmail.com>
Requires-Python: >=3.10
Requires-Dist: click>=8.1.8
Requires-Dist: peft>=0.14.0
Requires-Dist: torch>=2.6.0
Requires-Dist: transformers>=4.48.2
